wojak/__init__.py
wojak-0.2.dist-info/METADATA
wojak-0.2.dist-info/RECORD
wojak-0.2.dist-info/WHEEL
wojak-0.2.dist-info/top_level.txt
