Metadata-Version: 2.1
Name: wojak
Version: 0.2
Summary: request wojaks as a service
Home-page: https://yakz.cf/
Author: Jack (yak)
Author-email: oganesson1@icloud.com
License: ABSE
Platform: UNKNOWN
